elastic_zeroentropy/__init__.py
elastic_zeroentropy/cli.py
elastic_zeroentropy/config.py
elastic_zeroentropy/elasticsearch_client.py
elastic_zeroentropy/exceptions.py
elastic_zeroentropy/models.py
elastic_zeroentropy/reranker.py
elastic_zeroentropy/zeroentropy_client.py
elastic_zeroentropy-0.1.1.dist-info/METADATA
elastic_zeroentropy-0.1.1.dist-info/WHEEL
elastic_zeroentropy-0.1.1.dist-info/entry_points.txt
elastic_zeroentropy-0.1.1.dist-info/licenses/LICENSE
elastic_zeroentropy-0.1.1.dist-info/RECORD
