Metadata-Version: 2.4
Name: elastic-zeroentropy
Version: 0.1.1
Summary: Turn Elasticsearch into a smart search engine in 5 minutes with ZeroEntropy's LLM-powered reranking.
Project-URL: Homepage, https://github.com/vagabond11/elastic-zeroentropy
Project-URL: Documentation, https://github.com/vagabond11/elastic-zeroentropy#readme
Project-URL: Repository, https://github.com/vagabond11/elastic-zeroentropy
Project-URL: Issues, https://github.com/vagabond11/elastic-zeroentropy/issues
Author-email: Houssam Aït <houssam@example.com>
License-Expression: MIT
License-File: LICENSE
Keywords: ai,elasticsearch,llm,reranking,search,zeroentropy
Classifier: Development Status :: 4 - Beta
Classifier: Intended Audience :: Developers
Classifier: License :: OSI Approved :: MIT License
Classifier: Operating System :: OS Independent
Classifier: Programming Language :: Python :: 3
Classifier: Programming Language :: Python :: 3.8
Classifier: Programming Language :: Python :: 3.9
Classifier: Programming Language :: Python :: 3.10
Classifier: Programming Language :: Python :: 3.11
Classifier: Programming Language :: Python :: 3.12
Classifier: Topic :: Internet :: WWW/HTTP :: Indexing/Search
Classifier: Topic :: Scientific/Engineering :: Artificial Intelligence
Requires-Python: >=3.8
Requires-Dist: elasticsearch>=8.0.0
Requires-Dist: httpx>=0.24.0
Requires-Dist: pydantic-settings>=2.0.0
Requires-Dist: pydantic>=2.0.0
Requires-Dist: python-dotenv>=1.0.0
Requires-Dist: tenacity>=8.0.0
Provides-Extra: cli
Requires-Dist: click>=8.0.0; extra == 'cli'
Requires-Dist: rich>=13.0.0; extra == 'cli'
Provides-Extra: dev
Requires-Dist: bandit>=1.7.0; extra == 'dev'
Requires-Dist: black>=23.0.0; extra == 'dev'
Requires-Dist: flake8>=6.0.0; extra == 'dev'
Requires-Dist: isort>=5.12.0; extra == 'dev'
Requires-Dist: mypy>=1.0.0; extra == 'dev'
Requires-Dist: pre-commit>=3.0.0; extra == 'dev'
Requires-Dist: pytest-asyncio>=0.21.0; extra == 'dev'
Requires-Dist: pytest-cov>=4.0.0; extra == 'dev'
Requires-Dist: pytest-mock>=3.10.0; extra == 'dev'
Requires-Dist: pytest>=7.0.0; extra == 'dev'
Requires-Dist: safety>=2.0.0; extra == 'dev'
Provides-Extra: docs
Requires-Dist: mkdocs-material>=9.0.0; extra == 'docs'
Requires-Dist: mkdocs>=1.4.0; extra == 'docs'
Requires-Dist: mkdocstrings[python]>=0.20.0; extra == 'docs'
Provides-Extra: test
Requires-Dist: httpx[testing]>=0.24.0; extra == 'test'
Requires-Dist: pytest-asyncio>=0.21.0; extra == 'test'
Requires-Dist: pytest-cov>=4.0.0; extra == 'test'
Requires-Dist: pytest-mock>=3.10.0; extra == 'test'
Requires-Dist: pytest>=7.0.0; extra == 'test'
Requires-Dist: responses>=0.23.0; extra == 'test'
